{
    "title": "After Ten Years of Chopping Wood, Immortals Begged To Become My Disciples",
    "alternativeTitles": "Ten years after chopping wood, the fairy knelt down and begged me to accept her as a disciple, 劈柴十年，女仙跪地求我收她为徒",
    "typeOfWork": "مانهوا",
    "status": "",
    "releaseYear": "2023",
    "publisher": "n/a",
    "genres": [
        "اعادة احياء",
        "اكشن",
        "حريم",
        "فنون قتاليه"
    ],
    "summary": "استمررت بقطع الخشب يومًا بعد يوم طيلة عشرة سنوات، لقد تعبت ಠ╭╮ಠ ! وفجأة، بدأت الخالدات بالقدوم إليّ الواحدة تلو الأخرى (￣⊿￣)، إنهن يُردن أن يُصبحن تلميذاتي!",
    "publishingDate": "مارس 7, 2024",
    "lastUpdateDate": "مارس 7, 2024"
}