{
    "title": "Skeleton Soldier Couldn’t Protect the Dungeon",
    "alternativeTitles": ", Gaikotsu heishi wa Danjon o mamorenakatta | Skeletal Soldiers Could Not Protect the Dungeon | Skeleton Soldier | The Skeleton Soldier Failed to Defend the Dungeon | 해골병사는 던전을 지키지 못했다 | 骸骨兵士はダンジョンを守れなかった Skeleton Soldier Could not Protect the Dungeon,Skeleton Soldier Couldnt Protect the Dungeon ,Skeleton Soldier Couldn't Protect the Dungeon",
    "typeOfWork": "مانهوا",
    "status": "",
    "releaseYear": "2023",
    "publisher": "n/a",
    "genres": [
        "Updating"
    ],
    "summary": "كان هدفه الوحيد حماية سيده، لكنه لم يملك القوة لفعل ذلك، لكن القدر كان يخبئ له أمرًا آخر، فقد أعطاه فرصة أخرى لتغيير مصيره وحماية سيده.",
    "publishingDate": "فبراير 14, 2024",
    "lastUpdateDate": "فبراير 14, 2024"
}