{
    "title": "Player That Can’t Level Up",
    "alternativeTitles": "اللاعب لا يستطيع الإرتقاء المستوى The Player That Can't Level Up Player Who Can't Level Up Player Who Can’t Level Up",
    "typeOfWork": "مانهوا",
    "status": "",
    "releaseYear": "2023",
    "publisher": "n/a",
    "genres": [
        "Updating"
    ],
    "summary": "كيم كي جيو أيقظ قدراته كـ لاعب في سن الثامنة عشر. تسلق البرج وأنهى البوابة واعتقد أن حياته تتجه لتصبح جيدة…أنهى البرنامج التعليمي ولايزال بالمستوى الأول. حتى بعد قتل الوحوش يوميًا مازال بالمستوى الأول. بعد مرور خمس سنوات لايزال بالمستوى الأول. “كيف أكون لاعبًا بحق الجحيم إذا لم يزد مستواي على الإطلاق؟”",
    "publishingDate": "أبريل 3, 2024",
    "lastUpdateDate": "أبريل 3, 2024"
}