{
    "title": "The Supreme Lord System",
    "alternativeTitles": "The Supreme System",
    "typeOfWork": "مانهوا",
    "status": "",
    "releaseYear": "2023",
    "publisher": "n/a",
    "genres": [
        "اثاره",
        "اكشن",
        "ايسكاى",
        "تاريخى",
        "خارق للطبيعه",
        "خيال",
        "زمكانى",
        "شونين",
        "فنون قتاليه",
        "قوة خارقة",
        "مانهوا"
    ],
    "summary": "النظام الأعلى . مع طاقة غامضة من نظام إخباري يدعى CNNBBC ، قام صبي عادي من الأرض بالسفر عبر الزمن وولد من جديد في أرض غريبة ، حيث بدأ رحلته للاستيلاء على الكنز ، وممارسة أقوى فنون القتال والوصول إلى ذروة حياته!",
    "publishingDate": "مارس 8, 2024",
    "lastUpdateDate": "مارس 8, 2024"
}