{
    "title": "Plundering The Heavens",
    "alternativeTitles": "Unknown",
    "typeOfWork": "مانها",
    "status": "",
    "releaseYear": "2023",
    "publisher": "n/a",
    "genres": [
        "Unknown"
    ],
    "summary": "يقول البعض أنه طاغية أسود في عالم الفنون القتالية والصقل، شخص من دون حس بالعدالة أو الشرف، بل والأكثر من ذلك أنه عار وصم الصاقلين ونبلهم! بينما البعض الآخر يرونه على أنه قمامة نانزان يحاول التظاهر بالكمـال، تابع للصاقلين الشيطانيين، ومرتكب لكافة أنواع الجرائم! أجل واسمــه الوحيد الذي ينبغي على المرء تذكره هو فانغ شينغ!",
    "publishingDate": "فبراير 28, 2024",
    "lastUpdateDate": "فبراير 28, 2024"
}