{
    "title": "Necromancer Academy’s Genius Summoner",
    "alternativeTitles": "Necromancer Academy And The Genius Summoner",
    "typeOfWork": "مانهوا",
    "status": "",
    "releaseYear": "2023",
    "publisher": "n/a",
    "genres": [
        "اكشن",
        "حريم",
        "حياة مدرسية",
        "دراما",
        "رومانسى",
        "فنتازيا",
        "قوة خارقة",
        "كوميدى",
        "مغامرة"
    ],
    "summary": "بنى مستحضرو الأرواح اسماً لأنفسهم على أنهم مستخدموا سحرٍ مخيفون قادرون على إركاع إمبراطورية بأكلمها على ركبتيها. سيمون فولينتيا مستحضر أرواح بموهبة كامنة مذهلة! بعدما تم استقطابه من أجل أكاديمية مستحضري الأرواح، أصبح هذا العبقري جاهزاً لأن يُعتنى به وينتقل إلى مستوىً آخر. ولكن أيعقل أن تجذب مواهب سيمون المذهلة انتباه عواقب غير متوقعة البتة؟",
    "publishingDate": "أبريل 14, 2024",
    "lastUpdateDate": "أبريل 14, 2024"
}