{
    "title": "Damn Demonic Swords",
    "alternativeTitles": "Updating",
    "typeOfWork": "مانهوا",
    "status": "",
    "releaseYear": "2023",
    "publisher": "n/a",
    "genres": [
        "اكشن",
        "خيال",
        "شونين",
        "قتالات",
        "كوميديا",
        "مغامرة"
    ],
    "summary": "زيغار هو بطل يتجنب المشاكل بأي ثمن. الشيء الوحيد الذي يخاف منه هي الســــيوف الشيطانية، أسلحة شريرة تحاول السيطرة على حامليها. ولكن لسبب ما، لا تتوقف أبدًا عن مطاردته والالتصاق به. زيغار يريد فقط أن يعيش حياة هادئة، يقوم ببعض المهام الصغيرة ويبتعد عن المشاكل. لكن، دون قصد، يصبح مِــحور عدة أحداث تهز القارة الخيالية. “آه… اللعنة.” يندم، لكن لقد فات الأوان. إذا لم يستطع الهروب، لديه خيار واحد فقط",
    "publishingDate": "فبراير 24, 2024",
    "lastUpdateDate": "فبراير 24, 2024"
}