{
    "title": "The Abyssal Seed",
    "alternativeTitles": "Updating",
    "typeOfWork": "مانهوا",
    "status": "",
    "releaseYear": "2023",
    "publisher": "n/a",
    "genres": [
        "ارتقاء",
        "اكشن",
        "دموى",
        "روايه",
        "نظام",
        "نهاية العالم"
    ],
    "summary": "الغامض لناطحات السحاب إلى ظهور وحوش في أوقات وأماكن محددة، كان كل شيء يتطور وفقًا لسيناريو الرواية. أدرك تشانغ تين أنه من أجل البقاء على قيد الحياة، يجب عليه الحصول على القدرات الخاصة المذكورة في الرواية.\nباستخدام معرفته المسبقة بالحبكة، جلس بصبر في المكان الذي كان من المفترض أن تظهر فيه أولى بذور الهاوية. وعندما حان الوقت، نجح في الحصول على القدرات الاستثنائية الموجودة في الرواية،تابع العمل على فيكس مانجا، ليصبـــح واحدًا من أوائل الأفراد الذين يمتلكون القدرة على مواجهة التحديات في هذا العالم. النهاية المأساوية لا تمكن من التراجع عنها، ولكن تشانغ تين، مسلحًا بالمعرفة من الروايات التي قرأها، كان جاهزًا لمواجهة الختام القريب. مع ، اقتراب الحبكة التي قابلها في الروايات من ذروتها، على وشك الكشف عن أصل بذور الهاوية، مكشوفًا كل الأسرار المحيطة بنهاية العالم الوشيكة!",
    "publishingDate": "فبراير 12, 2024",
    "lastUpdateDate": "فبراير 12, 2024"
}